{
  "id": "fortinet_fgt_security_v5_kvp",
  "vendor": "fortinet",
  "model": "fgt",
  "logtype": "threat",
  "version": "v5",
  "format": "KeyValue2",
  "description": "Fortinet FortiGate Security v5 KeyValue2 - UTM DLP sensitive file",
  "sample": "date=2025-08-04T13:17:53,time=2025-08-04T13:17:53,devname=HQ-WIFI-FW,deviceid=FG60F4Q16000018,logid=0720018432,type=utm,subtype=dlp,pri=critical,vd=vdom2,src=192.168.1.51,dst=27.0.236.139,srcport=100,dstport=443,proto=TCP,service=smtp,dlpfile=tradesecret.xlsx,msg=DLP Triggered - Sensitive content,action=DENY",
  "parser": {
    "parserkey": "parserkey",
    "type": 1,
    "separator": "KeyValue2",
    "arrlength": -1
  },
  "fields": [
    { "position": 0,  "name": "date" },
    { "position": 1,  "name": "msg" },
    { "position": 2,  "name": "logid" },
    { "position": 3,  "name": "deviceid" },
    { "position": 4,  "name": "dstnip",      "orgname": "dst" },
    { "position": 5,  "name": "srcip",       "orgname": "src" },
    { "position": 6,  "name": "pri" },
    { "position": 7,  "name": "type" },
    { "position": 8,  "name": "vd" },
    { "position": 9,  "name": "srcport" },
    { "position": 10, "name": "dlpfile" },
    { "position": 11, "name": "subtype" },
    { "position": 12, "name": "service" },
    { "position": 13, "name": "prtc",        "orgname": "proto", "converttag": "toLowerCase" },
    { "position": 14, "name": "dstnport",    "orgname": "dstport" },
    { "position": 15, "name": "action",      "converttag": "toLowerCase" },
    { "position": 16, "name": "devname" },
    { "position": 17, "name": "time" },
    { "position": 18, "name": "vendor",      "converttag": "set:'fortinet'" },
    { "position": 19, "name": "model",       "converttag": "set:'fgt'" },
    { "position": 20, "name": "logtype",     "converttag": "set:'threat'" },
    { "position": 21, "name": "paserversion", "converttag": "set:'v5'" },
    { "position": 22, "name": "originallog", "converttag": "originalLog" },
    { "position": 23, "name": "parserinfo",  "converttag": "set:'fortinetfgtthreatv5keyvalue'" },
    { "position": 24, "name": "eqptype",     "converttag": "copy:'type'" },
    { "position": 25, "name": "attacknm",    "converttag": "copy:'msg'" }
  ]
}
